AUTHORS
COPYING
INSTALL
MANIFEST.in
NEWS
README
ez_setup.py
setup.cfg
setup.py
YYReview.egg-info/PKG-INFO
YYReview.egg-info/SOURCES.txt
YYReview.egg-info/dependency_links.txt
YYReview.egg-info/entry_points.txt
YYReview.egg-info/top_level.txt
contrib/P4Tool.txt
contrib/internal/release.py
rbtools/__init__.py
rbtools/postreview.py
rbtools/tests.py
rbtools/api/__init__.py
rbtools/api/errors.py
rbtools/clients/__init__.py
rbtools/clients/clearcase.py
rbtools/clients/cvs.py
rbtools/clients/git.py
rbtools/clients/mercurial.py
rbtools/clients/perforce.py
rbtools/clients/plastic.py
rbtools/clients/svn.py
rbtools/clients/tests.py
rbtools/utils/__init__.py
rbtools/utils/checks.py
rbtools/utils/filesystem.py
rbtools/utils/process.py
rbtools/utils/testbase.py
rbtools/utils/tests.py