Metadata-Version: 1.0
Name: YYReview
Version: 1.0
Summary: Command line tools for use with Review Board for YY
Home-page: UNKNOWN
Author: Shaoyan Huang
Author-email: huangshaoyan1982@gmail.com
License: MIT
Platform: UNKNOWN
Classifier: Development Status :: 3 - Alpha
Classifier: Environment :: Console
Classifier: Intended Audience :: Developers
Classifier: License :: OSI Approved :: MIT License
Classifier: Operating System :: OS Independent
Classifier: Programming Language :: Python
Classifier: Topic :: Software Development
